moe_parsers/__init__.py
moe_parsers/classes.py
moe_parsers/moe.py
moe_parsers/providers/__init__.py
moe_parsers/providers/aniboom.py
moe_parsers/providers/animego.py
moe_parsers/providers/kodik.py
tests/__init__.py
tests/unit/__init__.py
tests/unit/test_aniboom.py
tests/unit/test_animego.py
tests/unit/test_kodik.py
moe_parsers-2024.12.3.dist-info/METADATA
moe_parsers-2024.12.3.dist-info/WHEEL
moe_parsers-2024.12.3.dist-info/top_level.txt
moe_parsers-2024.12.3.dist-info/RECORD
