Metadata-Version: 2.1
Name: moe-parsers
Version: 2024.12.3
Summary: Parsing anime and getting video made easy
Home-page: https://github.com/nichind/moe-parsers
Author: nichind
Author-email: nichinddev@gmail.com
Keywords: aniboom,kodik,animego,moe,parser,anime,async
Classifier: Programming Language :: Python :: 3.11
Classifier: License :: OSI Approved :: MIT License
Classifier: Operating System :: OS Independent
Requires-Python: >=3.11
Requires-Dist: aiohttp
Requires-Dist: python-dotenv
Requires-Dist: beautifulsoup4
